{
"skeleton": { "hash": "c2kDvnbXA4PhH8ooC7NLVI33/mo", "spine": "3.6.48", "width": 130.44, "height": 140.4, "images": "" },
"bones": [
	{ "name": "root" },
	{ "name": "bone", "parent": "root", "length": 40.82, "rotation": 89.25, "x": 8.9, "y": 32.85 },
	{ "name": "bone2", "parent": "bone", "length": 39.2, "rotation": 0.75, "x": 46.72, "y": 0.08 },
	{ "name": "bone3", "parent": "bone", "length": 24.71, "rotation": 133.11, "x": 28.1, "y": 27.76 },
	{ "name": "bone4", "parent": "bone3", "length": 15.8, "rotation": -32.58, "x": 28.61, "y": -2.1 },
	{ "name": "bone5", "parent": "bone", "length": 40.39, "rotation": -143.44, "x": 40.06, "y": -24.18 },
	{ "name": "bone6", "parent": "bone", "length": 26.86, "rotation": 179.61, "x": -6.99, "y": 0.45 },
	{ "name": "bone7", "parent": "bone2", "length": 21.33, "rotation": -2.86, "x": 10.71, "y": -5.74 },
	{ "name": "bone8", "parent": "bone4", "length": 24.75, "rotation": -71.77, "x": 9.16, "y": -18.25 },
	{ "name": "bone9", "parent": "bone4", "length": 24.75, "rotation": -71.77, "x": 9.16, "y": -18.25 },
	{ "name": "bone10", "parent": "root", "length": 45.84, "rotation": 89.3, "x": 9.27, "y": 172.61 },
	{ "name": "bone11", "parent": "root", "length": 25.15, "rotation": 90, "x": -46.63, "y": 129.01 },
	{ "name": "bone12", "parent": "root", "length": 26.88, "rotation": 86.42, "x": 65.17, "y": 131.24 }
],
"slots": [
	{ "name": "foot", "bone": "bone6", "attachment": "foot" },
	{ "name": "lhand", "bone": "bone5", "attachment": "lhand" },
	{ "name": "rhand", "bone": "bone3", "attachment": "rhand" },
	{ "name": "body", "bone": "bone", "attachment": "body" },
	{ "name": "head", "bone": "bone2", "attachment": "head" },
	{ "name": "weapon", "bone": "bone4", "attachment": "weapon" },
	{ "name": "eyes", "bone": "bone7", "attachment": "eyes" },
	{ "name": "on9", "bone": "bone8" },
	{ "name": "on10", "bone": "bone9" },
	{ "name": "zsh2", "bone": "bone10" },
	{ "name": "zshi1", "bone": "bone12" },
	{ "name": "zshi2", "bone": "bone11" }
],
"skins": {
	"default": {
		"body": {
			"body": { "x": 37.03, "y": 9.39, "rotation": -89.25, "width": 127, "height": 140 }
		},
		"eyes": {
			"eyes": { "x": -20.64, "y": 14.61, "rotation": -87.14, "width": 130, "height": 140 },
			"eyesBad": { "x": -20.71, "y": 16.03, "rotation": -87.14, "width": 130, "height": 140 }
		},
		"foot": {
			"foot": { "x": -43.95, "y": -9.25, "rotation": 91.15, "width": 127, "height": 140 }
		},
		"head": {
			"head": { "x": -9.57, "y": 9.44, "rotation": -90, "width": 130, "height": 140 }
		},
		"lhand": {
			"lhand": { "x": -17.56, "y": -28.77, "rotation": 54.2, "width": 127, "height": 140 }
		},
		"on10": {
			"on9": { "x": 6.09, "y": 0.38, "rotation": 71.77, "width": 100, "height": 100 }
		},
		"on9": {
			"on9": { "x": 6.09, "y": 0.38, "rotation": 71.77, "width": 100, "height": 100 }
		},
		"rhand": {
			"rhand": { "x": -19.51, "y": 6.04, "rotation": 137.64, "width": 127, "height": 140 }
		},
		"weapon": {
			"weapon": { "x": -44.93, "y": -19.05, "rotation": 170.22, "width": 127, "height": 140 }
		},
		"zsh2": {
			"zsh2": { "x": 19.02, "y": -0.89, "rotation": -89.3, "width": 73, "height": 93 }
		},
		"zshi1": {
			"zshi1": { "x": 3, "y": -3.17, "rotation": -86.42, "width": 66, "height": 67 }
		},
		"zshi2": {
			"zshi1": { "x": 5.03, "y": -1.12, "rotation": -90, "width": 66, "height": 67 }
		}
	}
},
"animations": {
	"airAttack": {
		"slots": {
			"on9": {
				"color": [
					{ "time": 0.2667, "color": "ffffffff" },
					{ "time": 0.4, "color": "ffffff00" }
				],
				"attachment": [
					{ "time": 0.2667, "name": "on9" }
				]
			},
			"on10": {
				"color": [
					{ "time": 0.3333, "color": "ffffffff" },
					{ "time": 0.4667, "color": "ffffff00" }
				],
				"attachment": [
					{ "time": 0.3333, "name": "on9" }
				]
			}
		},
		"bones": {
			"bone": {
				"rotate": [
					{ "time": 0, "angle": 0, "curve": "stepped" },
					{ "time": 0.2667, "angle": 0, "curve": "stepped" },
					{ "time": 0.5, "angle": 0, "curve": "stepped" },
					{ "time": 0.6667, "angle": 0 }
				],
				"translate": [
					{ "time": 0, "x": 0, "y": 0, "curve": "stepped" },
					{ "time": 0.2667, "x": 0, "y": 0 },
					{ "time": 0.3333, "x": -6.15, "y": 0 },
					{ "time": 0.4, "x": -0.18, "y": 0 },
					{ "time": 0.4667, "x": -6.21, "y": 0 },
					{ "time": 0.5, "x": 0, "y": 0, "curve": "stepped" },
					{ "time": 0.6667, "x": 0, "y": 0 }
				],
				"scale": [
					{ "time": 0, "x": 1, "y": 1, "curve": "stepped" },
					{ "time": 0.2667, "x": 1, "y": 1, "curve": "stepped" },
					{ "time": 0.5, "x": 1, "y": 1, "curve": "stepped" },
					{ "time": 0.6667, "x": 1, "y": 1 }
				]
			},
			"bone6": {
				"rotate": [
					{ "time": 0, "angle": 0, "curve": "stepped" },
					{ "time": 0.2667, "angle": 0, "curve": "stepped" },
					{ "time": 0.5, "angle": 0, "curve": "stepped" },
					{ "time": 0.6667, "angle": 0 }
				],
				"translate": [
					{ "time": 0, "x": 0, "y": 0, "curve": "stepped" },
					{ "time": 0.2667, "x": 0, "y": 0, "curve": "stepped" },
					{ "time": 0.5, "x": 0, "y": 0, "curve": "stepped" },
					{ "time": 0.6667, "x": 0, "y": 0 }
				],
				"scale": [
					{ "time": 0, "x": 1, "y": 1, "curve": "stepped" },
					{ "time": 0.2667, "x": 1, "y": 1, "curve": "stepped" },
					{ "time": 0.5, "x": 1, "y": 1, "curve": "stepped" },
					{ "time": 0.6667, "x": 1, "y": 1 }
				]
			},
			"bone5": {
				"rotate": [
					{ "time": 0, "angle": 0, "curve": "stepped" },
					{ "time": 0.2667, "angle": 0, "curve": "stepped" },
					{ "time": 0.5, "angle": 0, "curve": "stepped" },
					{ "time": 0.6667, "angle": 0 }
				],
				"translate": [
					{ "time": 0, "x": 0, "y": 0, "curve": "stepped" },
					{ "time": 0.2667, "x": 0, "y": 0, "curve": "stepped" },
					{ "time": 0.5, "x": 0, "y": 0, "curve": "stepped" },
					{ "time": 0.6667, "x": 0, "y": 0 }
				],
				"scale": [
					{ "time": 0, "x": 1, "y": 1, "curve": "stepped" },
					{ "time": 0.2667, "x": 1, "y": 1, "curve": "stepped" },
					{ "time": 0.5, "x": 1, "y": 1, "curve": "stepped" },
					{ "time": 0.6667, "x": 1, "y": 1 }
				]
			},
			"bone4": {
				"rotate": [
					{ "time": 0, "angle": 0 },
					{ "time": 0.2667, "angle": 82.06, "curve": "stepped" },
					{ "time": 0.5, "angle": 82.06 },
					{ "time": 0.6667, "angle": 0 }
				],
				"translate": [
					{ "time": 0, "x": 0, "y": 0, "curve": "stepped" },
					{ "time": 0.2667, "x": 0, "y": 0, "curve": "stepped" },
					{ "time": 0.5, "x": 0, "y": 0, "curve": "stepped" },
					{ "time": 0.6667, "x": 0, "y": 0 }
				],
				"scale": [
					{ "time": 0, "x": 1, "y": 1, "curve": "stepped" },
					{ "time": 0.2667, "x": 1, "y": 1, "curve": "stepped" },
					{ "time": 0.5, "x": 1, "y": 1, "curve": "stepped" },
					{ "time": 0.6667, "x": 1, "y": 1 }
				]
			},
			"bone3": {
				"rotate": [
					{ "time": 0, "angle": 0 },
					{ "time": 0.2667, "angle": -114.35, "curve": "stepped" },
					{ "time": 0.5, "angle": -114.35 },
					{ "time": 0.6667, "angle": 0 }
				],
				"translate": [
					{ "time": 0, "x": 0, "y": 0, "curve": "stepped" },
					{ "time": 0.2667, "x": 0, "y": 0, "curve": "stepped" },
					{ "time": 0.5, "x": 0, "y": 0, "curve": "stepped" },
					{ "time": 0.6667, "x": 0, "y": 0 }
				],
				"scale": [
					{ "time": 0, "x": 1, "y": 1, "curve": "stepped" },
					{ "time": 0.2667, "x": 1, "y": 1, "curve": "stepped" },
					{ "time": 0.5, "x": 1, "y": 1, "curve": "stepped" },
					{ "time": 0.6667, "x": 1, "y": 1 }
				]
			},
			"bone2": {
				"rotate": [
					{ "time": 0, "angle": 0, "curve": "stepped" },
					{ "time": 0.2667, "angle": 0, "curve": "stepped" },
					{ "time": 0.5, "angle": 0, "curve": "stepped" },
					{ "time": 0.6667, "angle": 0 }
				],
				"translate": [
					{ "time": 0, "x": 0, "y": 0, "curve": "stepped" },
					{ "time": 0.2667, "x": 0, "y": 0, "curve": "stepped" },
					{ "time": 0.5, "x": 0, "y": 0, "curve": "stepped" },
					{ "time": 0.6667, "x": 0, "y": 0 }
				],
				"scale": [
					{ "time": 0, "x": 1, "y": 1, "curve": "stepped" },
					{ "time": 0.2667, "x": 1, "y": 1, "curve": "stepped" },
					{ "time": 0.5, "x": 1, "y": 1, "curve": "stepped" },
					{ "time": 0.6667, "x": 1, "y": 1 }
				]
			},
			"bone8": {
				"rotate": [
					{ "time": 0.2667, "angle": 0, "curve": "stepped" },
					{ "time": 0.4, "angle": 0 }
				],
				"translate": [
					{ "time": 0.2667, "x": -1.5, "y": -0.62 },
					{ "time": 0.4, "x": 0, "y": 0 }
				],
				"scale": [
					{ "time": 0.2667, "x": 0.353, "y": 0.353 },
					{ "time": 0.4, "x": 1, "y": 1 }
				]
			},
			"bone9": {
				"rotate": [
					{ "time": 0.3333, "angle": 0, "curve": "stepped" },
					{ "time": 0.4667, "angle": 0 }
				],
				"translate": [
					{ "time": 0.3333, "x": -1.5, "y": -0.62 },
					{ "time": 0.4667, "x": 0, "y": 0 }
				],
				"scale": [
					{ "time": 0.3333, "x": 0.353, "y": 0.353 },
					{ "time": 0.4667, "x": 1, "y": 1 }
				]
			}
		}
	},
	"attack": {
		"bones": {
			"bone": {
				"rotate": [
					{ "time": 0, "angle": 0 },
					{ "time": 0.1333, "angle": -5.32 },
					{ "time": 0.3667, "angle": 11.97 },
					{ "time": 0.6667, "angle": 0 }
				],
				"translate": [
					{ "time": 0, "x": 0, "y": 0, "curve": "stepped" },
					{ "time": 0.1333, "x": 0, "y": 0 },
					{ "time": 0.3667, "x": 0, "y": -3.52 },
					{ "time": 0.6667, "x": 0, "y": 0 }
				],
				"scale": [
					{ "time": 0, "x": 1, "y": 1, "curve": "stepped" },
					{ "time": 0.1333, "x": 1, "y": 1, "curve": "stepped" },
					{ "time": 0.6667, "x": 1, "y": 1 }
				]
			},
			"bone6": {
				"rotate": [
					{ "time": 0, "angle": 0, "curve": "stepped" },
					{ "time": 0.1333, "angle": 0 },
					{ "time": 0.1667, "angle": -350.79 },
					{ "time": 0.3667, "angle": -11 },
					{ "time": 0.6667, "angle": 0 }
				],
				"translate": [
					{ "time": 0, "x": 0, "y": 0, "curve": "stepped" },
					{ "time": 0.1333, "x": 0, "y": 0 },
					{ "time": 0.3667, "x": 4.31, "y": -0.86 },
					{ "time": 0.6667, "x": 0, "y": 0 }
				],
				"scale": [
					{ "time": 0, "x": 1, "y": 1, "curve": "stepped" },
					{ "time": 0.1333, "x": 1, "y": 1, "curve": "stepped" },
					{ "time": 0.6667, "x": 1, "y": 1 }
				]
			},
			"bone5": {
				"rotate": [
					{ "time": 0, "angle": 0, "curve": "stepped" },
					{ "time": 0.1333, "angle": 0 },
					{ "time": 0.3667, "angle": 14.62 },
					{ "time": 0.6667, "angle": 0 }
				],
				"translate": [
					{ "time": 0, "x": 0, "y": 0, "curve": "stepped" },
					{ "time": 0.1333, "x": 0, "y": 0, "curve": "stepped" },
					{ "time": 0.6667, "x": 0, "y": 0 }
				],
				"scale": [
					{ "time": 0, "x": 1, "y": 1, "curve": "stepped" },
					{ "time": 0.1333, "x": 1, "y": 1, "curve": "stepped" },
					{ "time": 0.6667, "x": 1, "y": 1 }
				]
			},
			"bone4": {
				"rotate": [
					{ "time": 0, "angle": 0 },
					{ "time": 0.1333, "angle": 44.5 },
					{ "time": 0.6667, "angle": 0 }
				],
				"translate": [
					{ "time": 0, "x": 0, "y": 0, "curve": "stepped" },
					{ "time": 0.1333, "x": 0, "y": 0, "curve": "stepped" },
					{ "time": 0.6667, "x": 0, "y": 0 }
				],
				"scale": [
					{ "time": 0, "x": 1, "y": 1, "curve": "stepped" },
					{ "time": 0.1333, "x": 1, "y": 1, "curve": "stepped" },
					{ "time": 0.6667, "x": 1, "y": 1 }
				]
			},
			"bone3": {
				"rotate": [
					{ "time": 0, "angle": 0 },
					{ "time": 0.1333, "angle": -91.36 },
					{ "time": 0.3667, "angle": -40.78 },
					{ "time": 0.6667, "angle": 0 }
				],
				"translate": [
					{ "time": 0, "x": 0, "y": 0, "curve": "stepped" },
					{ "time": 0.1333, "x": 0, "y": 0, "curve": "stepped" },
					{ "time": 0.6667, "x": 0, "y": 0 }
				],
				"scale": [
					{ "time": 0, "x": 1, "y": 1, "curve": "stepped" },
					{ "time": 0.1333, "x": 1, "y": 1, "curve": "stepped" },
					{ "time": 0.6667, "x": 1, "y": 1 }
				]
			},
			"bone2": {
				"rotate": [
					{ "time": 0, "angle": 0, "curve": "stepped" },
					{ "time": 0.1333, "angle": 0, "curve": "stepped" },
					{ "time": 0.6667, "angle": 0 }
				],
				"translate": [
					{ "time": 0, "x": 0, "y": 0, "curve": "stepped" },
					{ "time": 0.1333, "x": 0, "y": 0, "curve": "stepped" },
					{ "time": 0.6667, "x": 0, "y": 0 }
				],
				"scale": [
					{ "time": 0, "x": 1, "y": 1, "curve": "stepped" },
					{ "time": 0.1333, "x": 1, "y": 1, "curve": "stepped" },
					{ "time": 0.6667, "x": 1, "y": 1 }
				]
			}
		}
	},
	"defense": {
		"slots": {
			"eyes": {
				"attachment": [
					{ "time": 0, "name": "eyesBad" }
				]
			},
			"head": {
				"color": [
					{ "time": 0, "color": "ffffffff" },
					{ "time": 0.1667, "color": "ff1000ff" },
					{ "time": 0.3333, "color": "ffffffff" }
				]
			}
		},
		"bones": {
			"bone": {
				"rotate": [
					{ "time": 0, "angle": 0 },
					{ "time": 0.1667, "angle": -19.21 },
					{ "time": 0.3333, "angle": 0 }
				],
				"translate": [
					{ "time": 0, "x": 0, "y": 0 },
					{ "time": 0.1667, "x": 0, "y": -1.69 },
					{ "time": 0.3333, "x": 0, "y": 0 }
				],
				"scale": [
					{ "time": 0, "x": 1, "y": 1, "curve": "stepped" },
					{ "time": 0.3333, "x": 1, "y": 1 }
				]
			},
			"bone6": {
				"rotate": [
					{ "time": 0, "angle": 0 },
					{ "time": 0.1667, "angle": -338.29 },
					{ "time": 0.3333, "angle": 0 }
				],
				"translate": [
					{ "time": 0, "x": 0, "y": 0 },
					{ "time": 0.1667, "x": 2.31, "y": -1.41 },
					{ "time": 0.3333, "x": 0, "y": 0 }
				],
				"scale": [
					{ "time": 0, "x": 1, "y": 1, "curve": "stepped" },
					{ "time": 0.3333, "x": 1, "y": 1 }
				]
			},
			"bone5": {
				"rotate": [
					{ "time": 0, "angle": 0, "curve": "stepped" },
					{ "time": 0.3333, "angle": 0 }
				],
				"translate": [
					{ "time": 0, "x": 0, "y": 0, "curve": "stepped" },
					{ "time": 0.3333, "x": 0, "y": 0 }
				],
				"scale": [
					{ "time": 0, "x": 1, "y": 1, "curve": "stepped" },
					{ "time": 0.3333, "x": 1, "y": 1 }
				]
			},
			"bone3": {
				"rotate": [
					{ "time": 0, "angle": 0 },
					{ "time": 0.1667, "angle": -39 },
					{ "time": 0.3333, "angle": 0 }
				],
				"translate": [
					{ "time": 0, "x": 0, "y": 0, "curve": "stepped" },
					{ "time": 0.3333, "x": 0, "y": 0 }
				],
				"scale": [
					{ "time": 0, "x": 1, "y": 1, "curve": "stepped" },
					{ "time": 0.3333, "x": 1, "y": 1 }
				]
			},
			"bone7": {
				"rotate": [
					{ "time": 0, "angle": 0, "curve": "stepped" },
					{ "time": 0.3333, "angle": 0 }
				],
				"translate": [
					{ "time": 0, "x": 0, "y": 0, "curve": "stepped" },
					{ "time": 0.3333, "x": 0, "y": 0 }
				],
				"scale": [
					{ "time": 0, "x": 1, "y": 1, "curve": "stepped" },
					{ "time": 0.3333, "x": 1, "y": 1 }
				]
			},
			"bone2": {
				"rotate": [
					{ "time": 0, "angle": 0, "curve": "stepped" },
					{ "time": 0.3333, "angle": 0 }
				],
				"translate": [
					{ "time": 0, "x": 0, "y": 0, "curve": "stepped" },
					{ "time": 0.3333, "x": 0, "y": 0 }
				],
				"scale": [
					{ "time": 0, "x": 1, "y": 1, "curve": "stepped" },
					{ "time": 0.3333, "x": 1, "y": 1 }
				]
			}
		}
	},
	"die": {
		"slots": {
			"eyes": {
				"attachment": [
					{ "time": 0, "name": "eyesBad" }
				]
			}
		},
		"bones": {
			"bone": {
				"rotate": [
					{ "time": 0, "angle": 0 },
					{ "time": 0.3333, "angle": -71.84 }
				],
				"translate": [
					{ "time": 0, "x": 0, "y": 0 },
					{ "time": 0.3333, "x": -14.91, "y": -5.77 }
				],
				"scale": [
					{ "time": 0, "x": 1, "y": 1, "curve": "stepped" },
					{ "time": 0.3333, "x": 1, "y": 1 }
				]
			},
			"bone6": {
				"rotate": [
					{ "time": 0, "angle": 0 },
					{ "time": 0.3333, "angle": -8.47 }
				],
				"translate": [
					{ "time": 0, "x": 0, "y": 0, "curve": "stepped" },
					{ "time": 0.3333, "x": 0, "y": 0 }
				],
				"scale": [
					{ "time": 0, "x": 1, "y": 1, "curve": "stepped" },
					{ "time": 0.3333, "x": 1, "y": 1 }
				]
			},
			"bone5": {
				"rotate": [
					{ "time": 0, "angle": 0 },
					{ "time": 0.3333, "angle": 24.46 }
				],
				"translate": [
					{ "time": 0, "x": 0, "y": 0, "curve": "stepped" },
					{ "time": 0.3333, "x": 0, "y": 0 }
				],
				"scale": [
					{ "time": 0, "x": 1, "y": 1, "curve": "stepped" },
					{ "time": 0.3333, "x": 1, "y": 1 }
				]
			},
			"bone4": {
				"rotate": [
					{ "time": 0, "angle": 0, "curve": "stepped" },
					{ "time": 0.3333, "angle": 0 }
				],
				"translate": [
					{ "time": 0, "x": 0, "y": 0, "curve": "stepped" },
					{ "time": 0.3333, "x": 0, "y": 0 }
				],
				"scale": [
					{ "time": 0, "x": 1, "y": 1, "curve": "stepped" },
					{ "time": 0.3333, "x": 1, "y": 1 }
				]
			},
			"bone3": {
				"rotate": [
					{ "time": 0, "angle": 0 },
					{ "time": 0.3333, "angle": -63.44 }
				],
				"translate": [
					{ "time": 0, "x": 0, "y": 0, "curve": "stepped" },
					{ "time": 0.3333, "x": 0, "y": 0 }
				],
				"scale": [
					{ "time": 0, "x": 1, "y": 1, "curve": "stepped" },
					{ "time": 0.3333, "x": 1, "y": 1 }
				]
			},
			"bone7": {
				"rotate": [
					{ "time": 0, "angle": 0, "curve": "stepped" },
					{ "time": 0.3333, "angle": 0 }
				],
				"translate": [
					{ "time": 0, "x": 0, "y": 0, "curve": "stepped" },
					{ "time": 0.3333, "x": 0, "y": 0 }
				],
				"scale": [
					{ "time": 0, "x": 1, "y": 1, "curve": "stepped" },
					{ "time": 0.3333, "x": 1, "y": 1 }
				]
			},
			"bone2": {
				"rotate": [
					{ "time": 0, "angle": 0, "curve": "stepped" },
					{ "time": 0.3333, "angle": 0 }
				],
				"translate": [
					{ "time": 0, "x": 0, "y": 0, "curve": "stepped" },
					{ "time": 0.3333, "x": 0, "y": 0 }
				],
				"scale": [
					{ "time": 0, "x": 1, "y": 1, "curve": "stepped" },
					{ "time": 0.3333, "x": 1, "y": 1 }
				]
			}
		}
	},
	"miss": {
		"bones": {
			"bone": {
				"rotate": [
					{ "time": 0, "angle": 0 },
					{ "time": 0.1667, "angle": -3.75, "curve": "stepped" },
					{ "time": 0.3333, "angle": -3.75 },
					{ "time": 0.6667, "angle": 0 }
				],
				"translate": [
					{ "time": 0, "x": 0, "y": 0 },
					{ "time": 0.1667, "x": 26.36, "y": 0, "curve": "stepped" },
					{ "time": 0.3333, "x": 26.36, "y": 0 },
					{ "time": 0.6667, "x": 0, "y": 0 }
				],
				"scale": [
					{ "time": 0, "x": 1, "y": 1, "curve": "stepped" },
					{ "time": 0.1667, "x": 1, "y": 1, "curve": "stepped" },
					{ "time": 0.3333, "x": 1, "y": 1, "curve": "stepped" },
					{ "time": 0.6667, "x": 1, "y": 1 }
				]
			},
			"bone6": {
				"rotate": [
					{ "time": 0, "angle": 0 },
					{ "time": 0.1667, "angle": -3.75, "curve": "stepped" },
					{ "time": 0.3333, "angle": -3.75 },
					{ "time": 0.6667, "angle": 0 }
				],
				"translate": [
					{ "time": 0, "x": 0, "y": 0, "curve": "stepped" },
					{ "time": 0.1667, "x": 0, "y": 0, "curve": "stepped" },
					{ "time": 0.3333, "x": 0, "y": 0, "curve": "stepped" },
					{ "time": 0.6667, "x": 0, "y": 0 }
				],
				"scale": [
					{ "time": 0, "x": 1, "y": 1, "curve": "stepped" },
					{ "time": 0.1667, "x": 1, "y": 1, "curve": "stepped" },
					{ "time": 0.3333, "x": 1, "y": 1, "curve": "stepped" },
					{ "time": 0.6667, "x": 1, "y": 1 }
				]
			},
			"bone5": {
				"rotate": [
					{ "time": 0, "angle": 0 },
					{ "time": 0.1667, "angle": -3.75, "curve": "stepped" },
					{ "time": 0.3333, "angle": -3.75 },
					{ "time": 0.6667, "angle": 0 }
				],
				"translate": [
					{ "time": 0, "x": 0, "y": 0, "curve": "stepped" },
					{ "time": 0.1667, "x": 0, "y": 0, "curve": "stepped" },
					{ "time": 0.3333, "x": 0, "y": 0, "curve": "stepped" },
					{ "time": 0.6667, "x": 0, "y": 0 }
				],
				"scale": [
					{ "time": 0, "x": 1, "y": 1, "curve": "stepped" },
					{ "time": 0.1667, "x": 1, "y": 1, "curve": "stepped" },
					{ "time": 0.3333, "x": 1, "y": 1, "curve": "stepped" },
					{ "time": 0.6667, "x": 1, "y": 1 }
				]
			},
			"bone3": {
				"rotate": [
					{ "time": 0, "angle": 0 },
					{ "time": 0.1667, "angle": -3.75, "curve": "stepped" },
					{ "time": 0.3333, "angle": -3.75 },
					{ "time": 0.6667, "angle": 0 }
				],
				"translate": [
					{ "time": 0, "x": 0, "y": 0, "curve": "stepped" },
					{ "time": 0.1667, "x": 0, "y": 0, "curve": "stepped" },
					{ "time": 0.3333, "x": 0, "y": 0, "curve": "stepped" },
					{ "time": 0.6667, "x": 0, "y": 0 }
				],
				"scale": [
					{ "time": 0, "x": 1, "y": 1, "curve": "stepped" },
					{ "time": 0.1667, "x": 1, "y": 1, "curve": "stepped" },
					{ "time": 0.3333, "x": 1, "y": 1, "curve": "stepped" },
					{ "time": 0.6667, "x": 1, "y": 1 }
				]
			},
			"bone2": {
				"rotate": [
					{ "time": 0, "angle": 0 },
					{ "time": 0.1667, "angle": -3.75, "curve": "stepped" },
					{ "time": 0.3333, "angle": -3.75 },
					{ "time": 0.6667, "angle": 0 }
				],
				"translate": [
					{ "time": 0, "x": 0, "y": 0, "curve": "stepped" },
					{ "time": 0.1667, "x": 0, "y": 0, "curve": "stepped" },
					{ "time": 0.3333, "x": 0, "y": 0, "curve": "stepped" },
					{ "time": 0.6667, "x": 0, "y": 0 }
				],
				"scale": [
					{ "time": 0, "x": 1, "y": 1, "curve": "stepped" },
					{ "time": 0.1667, "x": 1, "y": 1, "curve": "stepped" },
					{ "time": 0.3333, "x": 1, "y": 1, "curve": "stepped" },
					{ "time": 0.6667, "x": 1, "y": 1 }
				]
			}
		}
	},
	"resurrection": {
		"slots": {
			"eyes": {
				"attachment": [
					{ "time": 0.3333, "name": "eyes" }
				]
			}
		},
		"bones": {
			"bone": {
				"rotate": [
					{ "time": 0, "angle": -71.84 },
					{ "time": 0.3333, "angle": 0 }
				],
				"translate": [
					{ "time": 0, "x": -14.91, "y": -5.77 },
					{ "time": 0.3333, "x": 0, "y": 0 }
				],
				"scale": [
					{ "time": 0, "x": 1, "y": 1, "curve": "stepped" },
					{ "time": 0.3333, "x": 1, "y": 1 }
				]
			},
			"bone6": {
				"rotate": [
					{ "time": 0, "angle": -8.47 },
					{ "time": 0.3333, "angle": 0 }
				],
				"translate": [
					{ "time": 0, "x": 0, "y": 0, "curve": "stepped" },
					{ "time": 0.3333, "x": 0, "y": 0 }
				],
				"scale": [
					{ "time": 0, "x": 1, "y": 1, "curve": "stepped" },
					{ "time": 0.3333, "x": 1, "y": 1 }
				]
			},
			"bone5": {
				"rotate": [
					{ "time": 0, "angle": 24.46 },
					{ "time": 0.3333, "angle": 0 }
				],
				"translate": [
					{ "time": 0, "x": 0, "y": 0, "curve": "stepped" },
					{ "time": 0.3333, "x": 0, "y": 0 }
				],
				"scale": [
					{ "time": 0, "x": 1, "y": 1, "curve": "stepped" },
					{ "time": 0.3333, "x": 1, "y": 1 }
				]
			},
			"bone4": {
				"rotate": [
					{ "time": 0, "angle": 0, "curve": "stepped" },
					{ "time": 0.3333, "angle": 0 }
				],
				"translate": [
					{ "time": 0, "x": 0, "y": 0, "curve": "stepped" },
					{ "time": 0.3333, "x": 0, "y": 0 }
				],
				"scale": [
					{ "time": 0, "x": 1, "y": 1, "curve": "stepped" },
					{ "time": 0.3333, "x": 1, "y": 1 }
				]
			},
			"bone3": {
				"rotate": [
					{ "time": 0, "angle": -63.44 },
					{ "time": 0.3333, "angle": 0 }
				],
				"translate": [
					{ "time": 0, "x": 0, "y": 0, "curve": "stepped" },
					{ "time": 0.3333, "x": 0, "y": 0 }
				],
				"scale": [
					{ "time": 0, "x": 1, "y": 1, "curve": "stepped" },
					{ "time": 0.3333, "x": 1, "y": 1 }
				]
			},
			"bone7": {
				"rotate": [
					{ "time": 0, "angle": 0, "curve": "stepped" },
					{ "time": 0.3333, "angle": 0 }
				],
				"translate": [
					{ "time": 0, "x": 0, "y": 0, "curve": "stepped" },
					{ "time": 0.3333, "x": 0, "y": 0 }
				],
				"scale": [
					{ "time": 0, "x": 1, "y": 1, "curve": "stepped" },
					{ "time": 0.3333, "x": 1, "y": 1 }
				]
			},
			"bone2": {
				"rotate": [
					{ "time": 0, "angle": 0, "curve": "stepped" },
					{ "time": 0.3333, "angle": 0 }
				],
				"translate": [
					{ "time": 0, "x": 0, "y": 0, "curve": "stepped" },
					{ "time": 0.3333, "x": 0, "y": 0 }
				],
				"scale": [
					{ "time": 0, "x": 1, "y": 1, "curve": "stepped" },
					{ "time": 0.3333, "x": 1, "y": 1 }
				]
			}
		}
	},
	"skill": {
		"slots": {
			"zsh2": {
				"color": [
					{
						"time": 0.1,
						"color": "ffffff00",
						"curve": [ 0.132, 0.12, 0.75, 1 ]
					},
					{ "time": 0.3333, "color": "ffffffff", "curve": "stepped" },
					{ "time": 0.4333, "color": "ffffffff" },
					{ "time": 0.6333, "color": "ffffff00" }
				],
				"attachment": [
					{ "time": 0.1, "name": "zsh2" }
				]
			},
			"zshi1": {
				"color": [
					{
						"time": 0.1,
						"color": "ffffff00",
						"curve": [ 0.132, 0.12, 0.75, 1 ]
					},
					{ "time": 0.3333, "color": "ffffffff", "curve": "stepped" },
					{ "time": 0.4333, "color": "ffffffff" },
					{ "time": 0.6333, "color": "ffffff00" }
				],
				"attachment": [
					{ "time": 0.1, "name": "zshi1" }
				]
			},
			"zshi2": {
				"color": [
					{
						"time": 0.1,
						"color": "ffffff00",
						"curve": [ 0.132, 0.12, 0.75, 1 ]
					},
					{ "time": 0.3333, "color": "ffffffff", "curve": "stepped" },
					{ "time": 0.4333, "color": "ffffffff" },
					{ "time": 0.6333, "color": "ffffff00" }
				],
				"attachment": [
					{ "time": 0.1, "name": "zshi1" }
				]
			}
		},
		"bones": {
			"bone": {
				"rotate": [
					{ "time": 0, "angle": 0, "curve": "stepped" },
					{ "time": 0.1, "angle": 0, "curve": "stepped" },
					{ "time": 0.5, "angle": 0, "curve": "stepped" },
					{ "time": 0.6333, "angle": 0 }
				],
				"translate": [
					{ "time": 0, "x": 0, "y": 0 },
					{ "time": 0.1, "x": 0, "y": 32.63, "curve": "stepped" },
					{ "time": 0.5, "x": 0, "y": 32.63 },
					{ "time": 0.6333, "x": 0, "y": 0 }
				],
				"scale": [
					{ "time": 0, "x": 1, "y": 1, "curve": "stepped" },
					{ "time": 0.1, "x": 1, "y": 1, "curve": "stepped" },
					{ "time": 0.5, "x": 1, "y": 1, "curve": "stepped" },
					{ "time": 0.6333, "x": 1, "y": 1 }
				]
			},
			"bone6": {
				"rotate": [
					{ "time": 0, "angle": 0, "curve": "stepped" },
					{ "time": 0.1, "angle": 0, "curve": "stepped" },
					{ "time": 0.5, "angle": 0, "curve": "stepped" },
					{ "time": 0.6333, "angle": 0 }
				],
				"translate": [
					{ "time": 0, "x": 0, "y": 0, "curve": "stepped" },
					{ "time": 0.1, "x": 0, "y": 0, "curve": "stepped" },
					{ "time": 0.5, "x": 0, "y": 0, "curve": "stepped" },
					{ "time": 0.6333, "x": 0, "y": 0 }
				],
				"scale": [
					{ "time": 0, "x": 1, "y": 1, "curve": "stepped" },
					{ "time": 0.1, "x": 1, "y": 1, "curve": "stepped" },
					{ "time": 0.5, "x": 1, "y": 1, "curve": "stepped" },
					{ "time": 0.6333, "x": 1, "y": 1 }
				]
			},
			"bone5": {
				"rotate": [
					{ "time": 0, "angle": 0 },
					{ "time": 0.1, "angle": 108.49, "curve": "stepped" },
					{ "time": 0.5, "angle": 108.49 },
					{ "time": 0.6333, "angle": 0 }
				],
				"translate": [
					{ "time": 0, "x": 0, "y": 0 },
					{ "time": 0.1, "x": -15.23, "y": 5.07, "curve": "stepped" },
					{ "time": 0.5, "x": -15.23, "y": 5.07 },
					{ "time": 0.6333, "x": 0, "y": 0 }
				],
				"scale": [
					{ "time": 0, "x": 1, "y": 1, "curve": "stepped" },
					{ "time": 0.1, "x": 1, "y": 1, "curve": "stepped" },
					{ "time": 0.5, "x": 1, "y": 1, "curve": "stepped" },
					{ "time": 0.6333, "x": 1, "y": 1 }
				]
			},
			"bone4": {
				"rotate": [
					{ "time": 0, "angle": 0, "curve": "stepped" },
					{ "time": 0.1, "angle": 0, "curve": "stepped" },
					{ "time": 0.5, "angle": 0, "curve": "stepped" },
					{ "time": 0.6333, "angle": 0 }
				],
				"translate": [
					{ "time": 0, "x": 0, "y": 0, "curve": "stepped" },
					{ "time": 0.1, "x": 0, "y": 0, "curve": "stepped" },
					{ "time": 0.5, "x": 0, "y": 0, "curve": "stepped" },
					{ "time": 0.6333, "x": 0, "y": 0 }
				],
				"scale": [
					{ "time": 0, "x": 1, "y": 1, "curve": "stepped" },
					{ "time": 0.1, "x": 1, "y": 1, "curve": "stepped" },
					{ "time": 0.5, "x": 1, "y": 1, "curve": "stepped" },
					{ "time": 0.6333, "x": 1, "y": 1 }
				]
			},
			"bone3": {
				"rotate": [
					{ "time": 0, "angle": 0 },
					{ "time": 0.1, "angle": -91.89, "curve": "stepped" },
					{ "time": 0.5, "angle": -91.89 },
					{ "time": 0.6333, "angle": 0 }
				],
				"translate": [
					{ "time": 0, "x": 0, "y": 0, "curve": "stepped" },
					{ "time": 0.1, "x": 0, "y": 0, "curve": "stepped" },
					{ "time": 0.5, "x": 0, "y": 0, "curve": "stepped" },
					{ "time": 0.6333, "x": 0, "y": 0 }
				],
				"scale": [
					{ "time": 0, "x": 1, "y": 1, "curve": "stepped" },
					{ "time": 0.1, "x": 1, "y": 1, "curve": "stepped" },
					{ "time": 0.5, "x": 1, "y": 1, "curve": "stepped" },
					{ "time": 0.6333, "x": 1, "y": 1 }
				]
			},
			"bone7": {
				"rotate": [
					{ "time": 0, "angle": 0, "curve": "stepped" },
					{ "time": 0.1, "angle": 0, "curve": "stepped" },
					{ "time": 0.5, "angle": 0, "curve": "stepped" },
					{ "time": 0.6333, "angle": 0 }
				],
				"translate": [
					{ "time": 0, "x": 0, "y": 0, "curve": "stepped" },
					{ "time": 0.1, "x": 0, "y": 0, "curve": "stepped" },
					{ "time": 0.5, "x": 0, "y": 0, "curve": "stepped" },
					{ "time": 0.6333, "x": 0, "y": 0 }
				],
				"scale": [
					{ "time": 0, "x": 1, "y": 1, "curve": "stepped" },
					{ "time": 0.1, "x": 1, "y": 1, "curve": "stepped" },
					{ "time": 0.5, "x": 1, "y": 1, "curve": "stepped" },
					{ "time": 0.6333, "x": 1, "y": 1 }
				]
			},
			"bone2": {
				"rotate": [
					{ "time": 0, "angle": 0, "curve": "stepped" },
					{ "time": 0.1, "angle": 0, "curve": "stepped" },
					{ "time": 0.5, "angle": 0, "curve": "stepped" },
					{ "time": 0.6333, "angle": 0 }
				],
				"translate": [
					{ "time": 0, "x": 0, "y": 0, "curve": "stepped" },
					{ "time": 0.1, "x": 0, "y": 0, "curve": "stepped" },
					{ "time": 0.5, "x": 0, "y": 0, "curve": "stepped" },
					{ "time": 0.6333, "x": 0, "y": 0 }
				],
				"scale": [
					{ "time": 0, "x": 1, "y": 1, "curve": "stepped" },
					{ "time": 0.1, "x": 1, "y": 1, "curve": "stepped" },
					{ "time": 0.5, "x": 1, "y": 1, "curve": "stepped" },
					{ "time": 0.6333, "x": 1, "y": 1 }
				]
			},
			"bone12": {
				"rotate": [
					{ "time": 0.1, "angle": 0, "curve": "stepped" },
					{ "time": 0.3333, "angle": 0, "curve": "stepped" },
					{ "time": 0.4333, "angle": 0 }
				],
				"translate": [
					{
						"time": 0.1,
						"x": 0,
						"y": 0,
						"curve": [ 0.132, 0.12, 0.75, 1 ]
					},
					{ "time": 0.3333, "x": 0, "y": 20.68, "curve": "stepped" },
					{ "time": 0.4333, "x": 0, "y": 20.68 },
					{ "time": 0.6333, "x": 0, "y": 29.07 }
				],
				"scale": [
					{ "time": 0.1, "x": 1, "y": 1, "curve": "stepped" },
					{ "time": 0.3333, "x": 1, "y": 1, "curve": "stepped" },
					{ "time": 0.4333, "x": 1, "y": 1 }
				]
			},
			"bone11": {
				"rotate": [
					{ "time": 0.1, "angle": 0, "curve": "stepped" },
					{ "time": 0.3333, "angle": 0, "curve": "stepped" },
					{ "time": 0.4333, "angle": 0 }
				],
				"translate": [
					{
						"time": 0.1,
						"x": 0,
						"y": 0,
						"curve": [ 0.132, 0.12, 0.75, 1 ]
					},
					{ "time": 0.3333, "x": 0, "y": 20.68, "curve": "stepped" },
					{ "time": 0.4333, "x": 0, "y": 20.68 },
					{ "time": 0.6333, "x": 0, "y": 29.07 }
				],
				"scale": [
					{ "time": 0.1, "x": 1, "y": 1, "curve": "stepped" },
					{ "time": 0.3333, "x": 1, "y": 1, "curve": "stepped" },
					{ "time": 0.4333, "x": 1, "y": 1 }
				]
			},
			"bone10": {
				"rotate": [
					{ "time": 0.1, "angle": 0, "curve": "stepped" },
					{ "time": 0.3333, "angle": 0, "curve": "stepped" },
					{ "time": 0.4333, "angle": 0 }
				],
				"translate": [
					{
						"time": 0.1,
						"x": 0,
						"y": 0,
						"curve": [ 0.132, 0.12, 0.75, 1 ]
					},
					{ "time": 0.3333, "x": 0, "y": 20.68, "curve": "stepped" },
					{ "time": 0.4333, "x": 0, "y": 20.68 },
					{ "time": 0.6333, "x": 0, "y": 29.07 }
				],
				"scale": [
					{ "time": 0.1, "x": 1, "y": 1, "curve": "stepped" },
					{ "time": 0.3333, "x": 1, "y": 1, "curve": "stepped" },
					{ "time": 0.4333, "x": 1, "y": 1 }
				]
			}
		}
	},
	"stand": {
		"slots": {
			"body": {
				"color": [
					{ "time": 0, "color": "ffffffff" }
				],
				"attachment": [
					{ "time": 0, "name": "body" }
				]
			},
			"eyes": {
				"color": [
					{ "time": 0, "color": "ffffffff" }
				],
				"attachment": [
					{ "time": 0, "name": "eyes" }
				]
			},
			"foot": {
				"color": [
					{ "time": 0, "color": "ffffffff" }
				],
				"attachment": [
					{ "time": 0, "name": "foot" }
				]
			},
			"head": {
				"color": [
					{ "time": 0, "color": "ffffffff" }
				],
				"attachment": [
					{ "time": 0, "name": "head" }
				]
			},
			"lhand": {
				"color": [
					{ "time": 0, "color": "ffffffff" }
				],
				"attachment": [
					{ "time": 0, "name": "lhand" }
				]
			},
			"rhand": {
				"color": [
					{ "time": 0, "color": "ffffffff" }
				],
				"attachment": [
					{ "time": 0, "name": "rhand" }
				]
			},
			"weapon": {
				"color": [
					{ "time": 0, "color": "ffffffff" }
				],
				"attachment": [
					{ "time": 0, "name": "weapon" }
				]
			}
		},
		"bones": {
			"bone": {
				"rotate": [
					{ "time": 0, "angle": 0, "curve": "stepped" },
					{ "time": 0.6667, "angle": 0 }
				],
				"translate": [
					{ "time": 0, "x": 0, "y": 0 },
					{ "time": 0.3333, "x": 0, "y": -5.27 },
					{ "time": 0.6667, "x": 0, "y": 0 }
				],
				"scale": [
					{ "time": 0, "x": 1, "y": 1, "curve": "stepped" },
					{ "time": 0.6667, "x": 1, "y": 1 }
				]
			},
			"bone6": {
				"rotate": [
					{ "time": 0, "angle": 0, "curve": "stepped" },
					{ "time": 0.6667, "angle": 0 }
				],
				"translate": [
					{ "time": 0, "x": 0, "y": 0 },
					{ "time": 0.3333, "x": 4.83, "y": 0.06 },
					{ "time": 0.6667, "x": 0, "y": 0 }
				],
				"scale": [
					{ "time": 0, "x": 1, "y": 1, "curve": "stepped" },
					{ "time": 0.6667, "x": 1, "y": 1 }
				]
			},
			"bone5": {
				"rotate": [
					{ "time": 0, "angle": 0 },
					{ "time": 0.3333, "angle": 4.51 },
					{ "time": 0.6667, "angle": 0 }
				],
				"translate": [
					{ "time": 0, "x": 0, "y": 0, "curve": "stepped" },
					{ "time": 0.6667, "x": 0, "y": 0 }
				],
				"scale": [
					{ "time": 0, "x": 1, "y": 1, "curve": "stepped" },
					{ "time": 0.6667, "x": 1, "y": 1 }
				]
			},
			"bone4": {
				"rotate": [
					{ "time": 0, "angle": 0, "curve": "stepped" },
					{ "time": 0.6667, "angle": 0 }
				],
				"translate": [
					{ "time": 0, "x": 0, "y": 0, "curve": "stepped" },
					{ "time": 0.6667, "x": 0, "y": 0 }
				],
				"scale": [
					{ "time": 0, "x": 1, "y": 1, "curve": "stepped" },
					{ "time": 0.6667, "x": 1, "y": 1 }
				]
			},
			"bone3": {
				"rotate": [
					{ "time": 0, "angle": 0 },
					{ "time": 0.3333, "angle": -19.7 },
					{ "time": 0.6667, "angle": 0 }
				],
				"translate": [
					{ "time": 0, "x": 0, "y": 0, "curve": "stepped" },
					{ "time": 0.6667, "x": 0, "y": 0 }
				],
				"scale": [
					{ "time": 0, "x": 1, "y": 1, "curve": "stepped" },
					{ "time": 0.6667, "x": 1, "y": 1 }
				]
			},
			"bone2": {
				"rotate": [
					{ "time": 0, "angle": 0, "curve": "stepped" },
					{ "time": 0.6667, "angle": 0 }
				],
				"translate": [
					{ "time": 0, "x": 0, "y": 0, "curve": "stepped" },
					{ "time": 0.6667, "x": 0, "y": 0 }
				],
				"scale": [
					{ "time": 0, "x": 1, "y": 1, "curve": "stepped" },
					{ "time": 0.6667, "x": 1, "y": 1 }
				]
			},
			"bone7": {
				"rotate": [
					{ "time": 0, "angle": 0 }
				],
				"translate": [
					{ "time": 0, "x": 0, "y": 0 }
				],
				"scale": [
					{ "time": 0, "x": 1, "y": 1 }
				]
			}
		}
	},
	"walk": {
		"bones": {
			"bone": {
				"rotate": [
					{ "time": 0, "angle": 0 },
					{ "time": 0.1667, "angle": 2.37 },
					{ "time": 0.3333, "angle": 0 },
					{ "time": 0.5, "angle": -3.09 },
					{ "time": 0.6667, "angle": 0 }
				],
				"translate": [
					{ "time": 0, "x": 0, "y": 0 },
					{ "time": 0.1667, "x": 0, "y": -4.04 },
					{ "time": 0.3333, "x": 0, "y": 0 },
					{ "time": 0.5, "x": 0, "y": -6.4 },
					{ "time": 0.6667, "x": 0, "y": 0 }
				],
				"scale": [
					{ "time": 0, "x": 1, "y": 1, "curve": "stepped" },
					{ "time": 0.3333, "x": 1, "y": 1, "curve": "stepped" },
					{ "time": 0.6667, "x": 1, "y": 1 }
				]
			},
			"bone6": {
				"rotate": [
					{ "time": 0, "angle": 0, "curve": "stepped" },
					{ "time": 0.3333, "angle": 0, "curve": "stepped" },
					{ "time": 0.6667, "angle": 0 }
				],
				"translate": [
					{ "time": 0, "x": 0, "y": 0, "curve": "stepped" },
					{ "time": 0.3333, "x": 0, "y": 0, "curve": "stepped" },
					{ "time": 0.6667, "x": 0, "y": 0 }
				],
				"scale": [
					{ "time": 0, "x": 1, "y": 1 },
					{ "time": 0.1667, "x": 1.09, "y": 1.09 },
					{ "time": 0.3333, "x": 1, "y": 1 },
					{ "time": 0.4667, "x": 1.114, "y": 1.027 },
					{ "time": 0.6667, "x": 1, "y": 1 }
				]
			},
			"bone5": {
				"rotate": [
					{ "time": 0, "angle": 0 },
					{ "time": 0.1667, "angle": 13.33 },
					{ "time": 0.3333, "angle": 0 },
					{ "time": 0.5, "angle": -11.15 },
					{ "time": 0.6667, "angle": 0 }
				],
				"translate": [
					{ "time": 0, "x": 0, "y": 0, "curve": "stepped" },
					{ "time": 0.3333, "x": 0, "y": 0, "curve": "stepped" },
					{ "time": 0.6667, "x": 0, "y": 0 }
				],
				"scale": [
					{ "time": 0, "x": 1, "y": 1, "curve": "stepped" },
					{ "time": 0.3333, "x": 1, "y": 1, "curve": "stepped" },
					{ "time": 0.6667, "x": 1, "y": 1 }
				]
			},
			"bone4": {
				"rotate": [
					{ "time": 0, "angle": 0, "curve": "stepped" },
					{ "time": 0.3333, "angle": 0, "curve": "stepped" },
					{ "time": 0.6667, "angle": 0 }
				],
				"translate": [
					{ "time": 0, "x": 0, "y": 0, "curve": "stepped" },
					{ "time": 0.3333, "x": 0, "y": 0, "curve": "stepped" },
					{ "time": 0.6667, "x": 0, "y": 0 }
				],
				"scale": [
					{ "time": 0, "x": 1, "y": 1, "curve": "stepped" },
					{ "time": 0.3333, "x": 1, "y": 1, "curve": "stepped" },
					{ "time": 0.6667, "x": 1, "y": 1 }
				]
			},
			"bone3": {
				"rotate": [
					{ "time": 0, "angle": 0 },
					{ "time": 0.1667, "angle": -9.31 },
					{ "time": 0.3333, "angle": 0 },
					{ "time": 0.5, "angle": 15.69 },
					{ "time": 0.6667, "angle": 0 }
				],
				"translate": [
					{ "time": 0, "x": 0, "y": 0, "curve": "stepped" },
					{ "time": 0.3333, "x": 0, "y": 0, "curve": "stepped" },
					{ "time": 0.6667, "x": 0, "y": 0 }
				],
				"scale": [
					{ "time": 0, "x": 1, "y": 1, "curve": "stepped" },
					{ "time": 0.3333, "x": 1, "y": 1, "curve": "stepped" },
					{ "time": 0.6667, "x": 1, "y": 1 }
				]
			},
			"bone7": {
				"rotate": [
					{ "time": 0, "angle": 0, "curve": "stepped" },
					{ "time": 0.3333, "angle": 0, "curve": "stepped" },
					{ "time": 0.6667, "angle": 0 }
				],
				"translate": [
					{ "time": 0, "x": 0, "y": 0, "curve": "stepped" },
					{ "time": 0.3333, "x": 0, "y": 0, "curve": "stepped" },
					{ "time": 0.6667, "x": 0, "y": 0 }
				],
				"scale": [
					{ "time": 0, "x": 1, "y": 1, "curve": "stepped" },
					{ "time": 0.3333, "x": 1, "y": 1, "curve": "stepped" },
					{ "time": 0.6667, "x": 1, "y": 1 }
				]
			},
			"bone2": {
				"rotate": [
					{ "time": 0, "angle": 0 },
					{ "time": 0.1667, "angle": -6.2 },
					{ "time": 0.3333, "angle": 0 },
					{ "time": 0.5, "angle": 1.44 },
					{ "time": 0.6667, "angle": 0 }
				],
				"translate": [
					{ "time": 0, "x": 0, "y": 0, "curve": "stepped" },
					{ "time": 0.3333, "x": 0, "y": 0, "curve": "stepped" },
					{ "time": 0.6667, "x": 0, "y": 0 }
				],
				"scale": [
					{ "time": 0, "x": 1, "y": 1, "curve": "stepped" },
					{ "time": 0.3333, "x": 1, "y": 1, "curve": "stepped" },
					{ "time": 0.6667, "x": 1, "y": 1 }
				]
			}
		}
	}
}
}